{
  "arch": "x86_64",
  "build": "ha36df97_2",
  "build_number": 2,
  "channel": "https://repo.anaconda.com/pkgs/main/win-64/",
  "constrains": [],
  "depends": [
    "icc_rt >=2022.1.0",
    "vc >=14.2,<15.0a0",
    "vs2015_runtime >=14.29.30133,<15.0a0",
    "zlib >=1.2.13,<2.0.0a0"
  ],
  "fn": "hdf5-1.14.5-ha36df97_2.conda",
  "license": "OTHER",
  "license_family": "BSD",
  "md5": "b24f8c0acdb94b74f8ee73d8a5d7d472",
  "name": "hdf5",
  "platform": "win32",
  "sha256": "c0e8e9f848a9b76c2183e898da2c4a1fe181a73b5c8cb31535f439f4205e6bc8",
  "size": 2250503,
  "subdir": "win-64",
  "timestamp": 1739226347000,
  "url": "https://repo.anaconda.com/pkgs/main/win-64/hdf5-1.14.5-ha36df97_2.conda",
  "version": "1.14.5"
}